nle/_pyconverter.cpython-311-aarch64-linux-gnu.so
nle/__init__.py
nle/version.py
nle/_pynethack.cpython-311-aarch64-linux-gnu.so
nle/libnethack.so
nle/nle_language_obsv.cpython-311-aarch64-linux-gnu.so
nle/language_wrapper/__init__.py
nle/language_wrapper/wrappers/__init__.py
nle/language_wrapper/wrappers/nle_language_wrapper.py
nle/language_wrapper/tests/test_nle_language_wrapper.py
nle/language_wrapper/tests/test_wrapper_menu.py
nle/language_wrapper/tests/__init__.py
nle/language_wrapper/tests/test_utils.py
nle/language_wrapper/tests/conftest.py
nle/language_wrapper/agents/__init__.py
nle/language_wrapper/agents/sample_factory/common.py
nle/language_wrapper/agents/sample_factory/__init__.py
nle/language_wrapper/agents/sample_factory/train.py
nle/language_wrapper/agents/sample_factory/env.py
nle/language_wrapper/agents/sample_factory/enjoy.py
nle/language_wrapper/agents/sample_factory/language_encoder.py
nle/language_wrapper/scripts/__init__.py
nle/language_wrapper/scripts/play.py
nle/agent/vtrace.py
nle/agent/__init__.py
nle/agent/agent.py
nle/nethackdir/dgn_comp
nle/nethackdir/xlogfile
nle/nethackdir/nhdat
nle/nethackdir/lev_comp
nle/nethackdir/record
nle/nethackdir/recover
nle/nethackdir/dlb
nle/nethackdir/logfile
nle/nethackdir/perm
nle/nethackdir/makedefs
nle/nethackdir/doc/dlb.txt
nle/nethackdir/doc/recover.txt
nle/nethackdir/doc/makedefs.txt
nle/nethackdir/doc/nethack.txt
nle/nethackdir/doc/dgn_comp.txt
nle/nethackdir/doc/lev_comp.txt
nle/nethackdir/dat/data.base
nle/nethackdir/dat/oracles.txt
nle/nethackdir/dat/Knight.des
nle/nethackdir/dat/Barb.des
nle/nethackdir/dat/Valkyrie.des
nle/nethackdir/dat/history
nle/nethackdir/dat/sokoban.des
nle/nethackdir/dat/help
nle/nethackdir/dat/symbols
nle/nethackdir/dat/opthelp
nle/nethackdir/dat/tower.des
nle/nethackdir/dat/Caveman.des
nle/nethackdir/dat/wizhelp
nle/nethackdir/dat/yendor.des
nle/nethackdir/dat/Tourist.des
nle/nethackdir/dat/license
balrog_nle-0.9.0.dist-info/METADATA
balrog_nle-0.9.0.dist-info/LICENSE
balrog_nle-0.9.0.dist-info/RECORD
balrog_nle-0.9.0.dist-info/WHEEL
balrog_nle-0.9.0.dist-info/entry_points.txt
balrog_nle-0.9.0.dist-info/top_level.txt
