Metadata-Version: 2.1
Name: balrog_nle
Version: 0.9.0
Summary: BALROG version of The NetHack Learning Environment (NLE)
Home-page: https://github.com/balrog-ai/nle
Author: The NLE Dev Team and BALROG
License: NetHack General Public License
Classifier: License :: OSI Approved :: Nethack General Public License
Classifier: Development Status :: 5 - Production/Stable
Classifier: Operating System :: POSIX :: Linux
Classifier: Operating System :: MacOS
Classifier: Programming Language :: Python :: 3
Classifier: Programming Language :: Python :: 3.8
Classifier: Programming Language :: Python :: 3.9
Classifier: Programming Language :: Python :: 3.10
Classifier: Programming Language :: Python :: 3.11
Classifier: Programming Language :: C
Classifier: Programming Language :: C++
Classifier: Topic :: Scientific/Engineering :: Artificial Intelligence
Classifier: Topic :: Games/Entertainment
Requires-Python: >=3.8
License-File: LICENSE
Requires-Dist: pybind11>=2.2
Requires-Dist: numpy>=1.16
Requires-Dist: gym==0.23
Provides-Extra: dev
Requires-Dist: pre-commit>=2.0.1; extra == "dev"
Requires-Dist: isort>=5.13.2; extra == "dev"
Requires-Dist: cmake_format>=0.6.10; extra == "dev"
Requires-Dist: memory-profiler>=0.60.0; extra == "dev"
Requires-Dist: pytest>=6.2.5; extra == "dev"
Requires-Dist: pytest-benchmark>=3.4.1; extra == "dev"
Requires-Dist: sphinx>=2.4.4; extra == "dev"
Requires-Dist: sphinx-rtd-theme>=0.4.3; extra == "dev"
Requires-Dist: setuptools>=69.5.1; extra == "dev"
Requires-Dist: ruff>=0.4.3; extra == "dev"
Provides-Extra: agent
Requires-Dist: torch>=1.3.1; extra == "agent"
Provides-Extra: all
Requires-Dist: pre-commit>=2.0.1; extra == "all"
Requires-Dist: isort>=5.13.2; extra == "all"
Requires-Dist: cmake_format>=0.6.10; extra == "all"
Requires-Dist: memory-profiler>=0.60.0; extra == "all"
Requires-Dist: pytest>=6.2.5; extra == "all"
Requires-Dist: pytest-benchmark>=3.4.1; extra == "all"
Requires-Dist: sphinx>=2.4.4; extra == "all"
Requires-Dist: sphinx-rtd-theme>=0.4.3; extra == "all"
Requires-Dist: setuptools>=69.5.1; extra == "all"
Requires-Dist: ruff>=0.4.3; extra == "all"
Requires-Dist: torch>=1.3.1; extra == "all"
